dynSboxGA/__init__.py
dynSboxGA/sbox.py
dynsboxga-0.1.2.dist-info/licenses/LICENSE
dynsboxga-0.1.2.dist-info/METADATA
dynsboxga-0.1.2.dist-info/WHEEL
dynsboxga-0.1.2.dist-info/entry_points.txt
dynsboxga-0.1.2.dist-info/top_level.txt
dynsboxga-0.1.2.dist-info/RECORD
